{
  "rooms": [
    {
      "id": 1,
      "title": "Hotel 1",
      "image": "https://a0.muscache.com/im/pictures/6dc4f6cb-5eb3-4c26-8dbc-17d738c093c8.jpg?im_w=720",
      "place": "VietNam",
      "price": "500$",
      "category": "Beach"
    },
    {
      "id": 2,
      "title": "Hotel 2",
      "image": "https://a0.muscache.com/im/pictures/a1d94df4-0001-47ef-a45e-21db63919e79.jpg?im_w=720",
      "place": "ThaiLand",
      "price": "550$"
    },
    {
      "id": 3,
      "title": "Hotel 3",
      "image": "https://a0.muscache.com/im/pictures/9fd1caf8-fccc-42c6-8cc2-a5c46ee1d29a.jpg?im_w=720",
      "place": "VietNam",
      "price": "500$"
    },
    {
      "id": 4,
      "title": "Hotel 4",
      "image": "https://a0.muscache.com/im/pictures/miso/Hosting-51947919/original/dfee1cf4-9b48-4c64-9353-dc961e9242fc.jpeg?im_w=720",
      "place": "United States",
      "price": "600$"
    },
    {
      "id": 5,
      "title": "Hotel 5",
      "image": "https://a0.muscache.com/im/pictures/8fb5846e-bb22-43d0-97f7-8a53aa86880f.jpg?im_w=720",
      "place": "VietNam",
      "price": "300$"
    },
    {
      "id": 6,
      "title": "Hotel 6",
      "image": "https://a0.muscache.com/im/pictures/0b65b1cd-0787-45c6-87a1-da3ff9e96760.jpg?im_w=720",
      "place": "Philippines",
      "price": "400$"
    },
    {
      "id": 7,
      "title": "Hotel 7",
      "image": "https://a0.muscache.com/im/pictures/48097969/cb846919_original.jpg?im_w=720",
      "place": "VietNam",
      "price": "300$",
      "category": "Windmills"
    },
    {
      "id": 8,
      "image": "https://a0.muscache.com/im/pictures/miso/Hosting-581480098379191226/original/80efcfcd-b88f-4b09-bb33-80e12f537cf5.jpeg?im_w=720",
      "title": "Hotel 8",
      "place": "VietNam",
      "price": "400$",
      "category": "Countryside"
    },
    {
      "id": 9,
      "image": "https://a0.muscache.com/im/pictures/prohost-api/Hosting-638051965796540359/original/aebf1873-cf48-4f53-a9de-6397096db82c.jpeg?im_w=720",
      "title": "Hotel 9",
      "place": "VietNam",
      "price": "450$"
    },
    {
      "id": 10,
      "image": "https://a0.muscache.com/im/pictures/miso/Hosting-5264493/original/10d2c21f-84c2-46c5-b20b-b51d1c2c971a.jpeg?im_w=720",
      "title": "Hotel 10",
      "place": "Russia",
      "price": "500$",
      "category": "Windmills"
    },
    {
      "id": 11,
      "image": "https://a0.muscache.com/im/pictures/miso/Hosting-611863153717289583/original/60a1c4d6-4210-44cd-ac92-63fac20d0b66.jpeg?im_w=720",
      "title": "Hotel 11",
      "place": "VietNam",
      "price": "400$",
      "category": "Beach"
    },
    {
      "id": 12,
      "title": "Hotel 12",
      "image": "https://a0.muscache.com/im/pictures/miso/Hosting-852899544635683289/original/c627f47e-8ca9-4471-90d4-1fd987dd2362.jpeg?im_w=720",
      "place": "Philippines",
      "price": "400$",
      "category": "Islands"
    },
    {
      "id": 13,
      "title": "Hotel 13",
      "image": "https://a0.muscache.com/im/pictures/42a35068-5ad4-4c2f-bc87-9943040f0b8a.jpg?im_w=720",
      "place": "ThaiLand",
      "price": "600$",
      "category": "Islands"
    },
    {
      "id": 14,
      "title": "Hotel 14",
      "image": "https://a0.muscache.com/im/pictures/b92d546e-d530-4cce-9986-459f5aa73dc4.jpg?im_w=720",
      "place": "Vietnam",
      "price": "500$",
      "category": "Pools"
    }
  ]
}